traffsimpy/__init__.py
traffsimpy/components.py
traffsimpy/constants.py
traffsimpy/drawing.py
traffsimpy/math_and_util.py
traffsimpy/settings.py
traffsimpy/simulation.py
traffsimpy/resources/.DS_Store
traffsimpy/resources/chevron.svg
traffsimpy/resources/jbmono.ttf
traffsimpy-0.1.12.dist-info/LICENSE
traffsimpy-0.1.12.dist-info/METADATA
traffsimpy-0.1.12.dist-info/WHEEL
traffsimpy-0.1.12.dist-info/top_level.txt
traffsimpy-0.1.12.dist-info/RECORD
