Metadata-Version: 2.1
Name: traffsimpy
Version: 0.1.12
Summary: Simulate traffic flow
Author-email: Hippolyte Cosserat <hippolytecosserat@gmail.com>
License: MIT License
Project-URL: Homepage, https://github.com/hcosserat/traffsimpy
Keywords: simulation,traffic,vehicules,roads
Classifier: License :: OSI Approved :: MIT License
Classifier: Programming Language :: Python
Classifier: Programming Language :: Python :: 3
Requires-Python: >=3.10
License-File: LICENSE
Requires-Dist: colorama (>=0.4.6)
Requires-Dist: matplotlib (>=3.7.0)
Requires-Dist: numpy (>=1.24.2)
Requires-Dist: pandas (>=1.5.3)
Requires-Dist: pygame (>=2.1.3)
Requires-Dist: PyYAML (>=6.0)
Requires-Dist: webcolors (>=1.12)
